README.rst
setup.cfg
setup.py
aurora_data_api_orator/__init__.py
aurora_data_api_orator/exceptions.py
aurora_data_api_orator/mysql_error_codes.py
aurora_data_api_orator.egg-info/PKG-INFO
aurora_data_api_orator.egg-info/SOURCES.txt
aurora_data_api_orator.egg-info/dependency_links.txt
aurora_data_api_orator.egg-info/requires.txt
aurora_data_api_orator.egg-info/top_level.txt
test/test.py