Metadata-Version: 1.1
Name: aurora-data-api-orator
Version: 0.2.6
Summary: A Python DB-API 2.0 client for the AWS Aurora Serverless Data API
Home-page: https://github.com/fenestron/aurora-data-api-orator.git
Author: Andrey Kislyuk
Author-email: akislyuk@chanzuckerberg.com
License: Apache Software License
Platform: MacOS X
Platform: Posix
Classifier: Intended Audience :: Developers
Classifier: License :: OSI Approved :: Apache Software License
Classifier: Operating System :: MacOS :: MacOS X
Classifier: Operating System :: POSIX
Classifier: Programming Language :: Python
Classifier: Programming Language :: Python :: 2.7
Classifier: Programming Language :: Python :: 3.3
Classifier: Programming Language :: Python :: 3.4
Classifier: Programming Language :: Python :: 3.5
Classifier: Topic :: Software Development :: Libraries :: Python Modules
